{
    "Ar36": {
        "error": 0.0068820225223357205,
        "error_type": "",
        "fit": "previous",
        "references": [
            {
                "exclude": false,
                "record_id": "ba-01-A-1588"
            }
        ],
        "value": 0.004528588722085489
    },
    "Ar37": {
        "error": 0.009449527615266278,
        "error_type": "",
        "fit": "previous",
        "references": [
            {
                "exclude": false,
                "record_id": "ba-01-A-1588"
            }
        ],
        "value": 0.03190589441107143
    },
    "Ar38": {
        "error": 0.004213977649843758,
        "error_type": "",
        "fit": "previous",
        "references": [
            {
                "exclude": false,
                "record_id": "ba-01-A-1588"
            }
        ],
        "value": -0.003204721112796634
    },
    "Ar39": {
        "error": 0.013803229267118548,
        "error_type": "",
        "fit": "previous",
        "references": [
            {
                "exclude": false,
                "record_id": "ba-01-A-1588"
            }
        ],
        "value": -0.007292223345841814
    },
    "Ar40": {
        "error": 0.015862922159774452,
        "error_type": "",
        "fit": "previous",
        "references": [
            {
                "exclude": false,
                "record_id": "ba-01-A-1588"
            }
        ],
        "value": 2.5422081886371166
    }
}